[
	{
		"name": "Juliet Martin",
		"age": 45,
		"country": "Spain",
		"nb_child": 2
	},
	{
		"name": "Clementine Allen",
		"age": 63,
		"country": "Italy",
		"nb_child": 3
	},
	{
		"name": "Kiara George",
		"age": 7,
		"country": "Belgium",
		"nb_child": 4
	},
	{
		"name": "Len Acosta",
		"age": 31,
		"country": "United Kingdom",
		"nb_child": 2
	},
	{
		"name": "Mercedes Browning",
		"age": 18,
		"country": "Belgium",
		"nb_child": 1
	},
	{
		"name": "Wing Walker",
		"age": 56,
		"country": "Belgium",
		"nb_child": 3
	},
	{
		"name": "Lucian Reid",
		"age": 51,
		"country": "Belgium",
		"nb_child": 1
	},
	{
		"name": "Brenna Dorsey",
		"age": 100,
		"country": "Spain",
		"nb_child": 1
	},
	{
		"name": "Vanna Miles",
		"age": 96,
		"country": "United Kingdom",
		"nb_child": 4
	},
	{
		"name": "Ann Howell",
		"age": 30,
		"country": "France",
		"nb_child": 1
	},
	{
		"name": "Brett Shelton",
		"age": 30,
		"country": "Belgium",
		"nb_child": 2
	},
	{
		"name": "Autumn Rodgers",
		"age": 98,
		"country": "Germany",
		"nb_child": 3
	},
	{
		"name": "Rooney Sosa",
		"age": 79,
		"country": "Italy",
		"nb_child": 3
	},
	{
		"name": "Alexa Crawford",
		"age": 46,
		"country": "France",
		"nb_child": 1
	},
	{
		"name": "Cameran Gamble",
		"age": 45,
		"country": "United Kingdom",
		"nb_child": 2
	},
	{
		"name": "Lee Madden",
		"age": 79,
		"country": "Belgium",
		"nb_child": 2
	},
	{
		"name": "Oliver Riley",
		"age": 67,
		"country": "United Kingdom",
		"nb_child": 4
	},
	{
		"name": "Claudia Hooper",
		"age": 22,
		"country": "United Kingdom",
		"nb_child": 4
	},
	{
		"name": "Steel Wilkins",
		"age": 72,
		"country": "Germany",
		"nb_child": 1
	},
	{
		"name": "Bruno Hess",
		"age": 63,
		"country": "United Kingdom",
		"nb_child": 2
	},
	{
		"name": "Mark Browning",
		"age": 62,
		"country": "France",
		"nb_child": 1
	},
	{
		"name": "Ann Herring",
		"age": 88,
		"country": "Spain",
		"nb_child": 3
	},
	{
		"name": "Ian Hale",
		"age": 64,
		"country": "Spain",
		"nb_child": 3
	},
	{
		"name": "Zachery Phillips",
		"age": 62,
		"country": "United Kingdom",
		"nb_child": 1
	},
	{
		"name": "Rhea Marquez",
		"age": 87,
		"country": "United Kingdom",
		"nb_child": 1
	},
	{
		"name": "Hilel Marshall",
		"age": 21,
		"country": "Italy",
		"nb_child": 1
	},
	{
		"name": "Amy Smith",
		"age": 94,
		"country": "Germany",
		"nb_child": 2
	},
	{
		"name": "Rahim Edwards",
		"age": 65,
		"country": "Italy",
		"nb_child": 1
	},
	{
		"name": "Gemma Sargent",
		"age": 71,
		"country": "France",
		"nb_child": 1
	},
	{
		"name": "Wade Hodge",
		"age": 94,
		"country": "Germany",
		"nb_child": 4
	},
	{
		"name": "Harlan Ray",
		"age": 28,
		"country": "Italy",
		"nb_child": 1
	},
	{
		"name": "Graham Walter",
		"age": 5,
		"country": "France",
		"nb_child": 4
	},
	{
		"name": "Megan Blevins",
		"age": 18,
		"country": "France",
		"nb_child": 2
	},
	{
		"name": "Kenyon Gomez",
		"age": 44,
		"country": "United Kingdom",
		"nb_child": 3
	},
	{
		"name": "Alexander Carpenter",
		"age": 43,
		"country": "Belgium",
		"nb_child": 1
	},
	{
		"name": "Travis Herrera",
		"age": 99,
		"country": "United Kingdom",
		"nb_child": 3
	},
	{
		"name": "Rhiannon Wade",
		"age": 76,
		"country": "Italy",
		"nb_child": 1
	},
	{
		"name": "Ariana Fox",
		"age": 82,
		"country": "United Kingdom",
		"nb_child": 1
	},
	{
		"name": "Lee Morrow",
		"age": 15,
		"country": "Spain",
		"nb_child": 3
	},
	{
		"name": "Chase Chase",
		"age": 57,
		"country": "Germany",
		"nb_child": 4
	},
	{
		"name": "Bert Oconnor",
		"age": 14,
		"country": "United Kingdom",
		"nb_child": 4
	},
	{
		"name": "Daria Hood",
		"age": 42,
		"country": "Italy",
		"nb_child": 1
	},
	{
		"name": "Ivy Gonzalez",
		"age": 56,
		"country": "France",
		"nb_child": 4
	},
	{
		"name": "Lacy Simon",
		"age": 98,
		"country": "Italy",
		"nb_child": 1
	},
	{
		"name": "Josiah Hayden",
		"age": 78,
		"country": "Italy",
		"nb_child": 2
	},
	{
		"name": "May Herrera",
		"age": 56,
		"country": "United Kingdom",
		"nb_child": 1
	},
	{
		"name": "Sonia Humphrey",
		"age": 43,
		"country": "Germany",
		"nb_child": 2
	},
	{
		"name": "Vladimir Campbell",
		"age": 11,
		"country": "Italy",
		"nb_child": 4
	},
	{
		"name": "Idola Giles",
		"age": 7,
		"country": "Italy",
		"nb_child": 2
	},
	{
		"name": "Pamela Vance",
		"age": 84,
		"country": "United Kingdom",
		"nb_child": 4
	},
	{
		"name": "Dustin Oneil",
		"age": 24,
		"country": "Spain",
		"nb_child": 1
	},
	{
		"name": "Hamilton Mcgowan",
		"age": 95,
		"country": "Belgium",
		"nb_child": 4
	},
	{
		"name": "Leandra Cannon",
		"age": 89,
		"country": "United Kingdom",
		"nb_child": 4
	},
	{
		"name": "Mira Simon",
		"age": 94,
		"country": "Spain",
		"nb_child": 3
	},
	{
		"name": "Wanda Franklin",
		"age": 62,
		"country": "France",
		"nb_child": 1
	},
	{
		"name": "Heather Mcmillan",
		"age": 8,
		"country": "United Kingdom",
		"nb_child": 2
	},
	{
		"name": "Cecilia Lowery",
		"age": 64,
		"country": "Spain",
		"nb_child": 4
	},
	{
		"name": "Nissim Patrick",
		"age": 74,
		"country": "Italy",
		"nb_child": 4
	},
	{
		"name": "Berk Webster",
		"age": 83,
		"country": "Germany",
		"nb_child": 4
	},
	{
		"name": "Barclay Velasquez",
		"age": 99,
		"country": "Spain",
		"nb_child": 1
	},
	{
		"name": "Gannon Cortez",
		"age": 89,
		"country": "Belgium",
		"nb_child": 1
	},
	{
		"name": "Zelenia Adkins",
		"age": 32,
		"country": "Belgium",
		"nb_child": 4
	},
	{
		"name": "Shaeleigh Carrillo",
		"age": 3,
		"country": "Belgium",
		"nb_child": 4
	},
	{
		"name": "Blossom English",
		"age": 53,
		"country": "Germany",
		"nb_child": 2
	},
	{
		"name": "Ross Lowe",
		"age": 65,
		"country": "Belgium",
		"nb_child": 1
	},
	{
		"name": "Nelle Faulkner",
		"age": 27,
		"country": "Germany",
		"nb_child": 1
	},
	{
		"name": "Linda Cleveland",
		"age": 78,
		"country": "Spain",
		"nb_child": 1
	},
	{
		"name": "Guinevere Maynard",
		"age": 24,
		"country": "Belgium",
		"nb_child": 2
	},
	{
		"name": "Lucas Mcgowan",
		"age": 12,
		"country": "Spain",
		"nb_child": 4
	},
	{
		"name": "Blaine Hammond",
		"age": 89,
		"country": "France",
		"nb_child": 3
	},
	{
		"name": "Kimberly Rivera",
		"age": 13,
		"country": "Belgium",
		"nb_child": 4
	},
	{
		"name": "Oscar Barron",
		"age": 92,
		"country": "United Kingdom",
		"nb_child": 2
	},
	{
		"name": "Leonard Mitchell",
		"age": 15,
		"country": "Italy",
		"nb_child": 1
	},
	{
		"name": "Maggie Stephens",
		"age": 90,
		"country": "France",
		"nb_child": 2
	},
	{
		"name": "Haley Greer",
		"age": 76,
		"country": "Italy",
		"nb_child": 3
	},
	{
		"name": "Julian Riddle",
		"age": 29,
		"country": "France",
		"nb_child": 1
	},
	{
		"name": "Chava Ellison",
		"age": 91,
		"country": "Germany",
		"nb_child": 3
	},
	{
		"name": "Emery Mcintosh",
		"age": 32,
		"country": "Spain",
		"nb_child": 1
	},
	{
		"name": "Brady Harding",
		"age": 55,
		"country": "Belgium",
		"nb_child": 4
	},
	{
		"name": "Alexa Carney",
		"age": 26,
		"country": "Belgium",
		"nb_child": 2
	},
	{
		"name": "Levi Barker",
		"age": 44,
		"country": "France",
		"nb_child": 2
	},
	{
		"name": "Aimee Nicholson",
		"age": 11,
		"country": "Spain",
		"nb_child": 4
	},
	{
		"name": "Carolyn Sloan",
		"age": 53,
		"country": "Germany",
		"nb_child": 1
	},
	{
		"name": "Wesley Koch",
		"age": 20,
		"country": "Italy",
		"nb_child": 3
	},
	{
		"name": "Vincent Jimenez",
		"age": 72,
		"country": "Germany",
		"nb_child": 4
	},
	{
		"name": "Barry Fitzgerald",
		"age": 98,
		"country": "Italy",
		"nb_child": 2
	},
	{
		"name": "Russell Compton",
		"age": 98,
		"country": "Spain",
		"nb_child": 1
	},
	{
		"name": "Morgan Perkins",
		"age": 73,
		"country": "France",
		"nb_child": 3
	},
	{
		"name": "Martha Howard",
		"age": 100,
		"country": "United Kingdom",
		"nb_child": 4
	},
	{
		"name": "Garth Curtis",
		"age": 39,
		"country": "Belgium",
		"nb_child": 1
	},
	{
		"name": "Nora Parks",
		"age": 94,
		"country": "Italy",
		"nb_child": 2
	},
	{
		"name": "Elaine Delacruz",
		"age": 53,
		"country": "Belgium",
		"nb_child": 4
	},
	{
		"name": "Cameron England",
		"age": 14,
		"country": "France",
		"nb_child": 2
	},
	{
		"name": "Miriam Lara",
		"age": 46,
		"country": "Italy",
		"nb_child": 3
	},
	{
		"name": "Natalie Shields",
		"age": 54,
		"country": "France",
		"nb_child": 2
	},
	{
		"name": "Len Schroeder",
		"age": 98,
		"country": "Belgium",
		"nb_child": 2
	},
	{
		"name": "Merrill Downs",
		"age": 10,
		"country": "Germany",
		"nb_child": 4
	},
	{
		"name": "Wynter Flynn",
		"age": 83,
		"country": "Italy",
		"nb_child": 2
	},
	{
		"name": "Amir Floyd",
		"age": 42,
		"country": "Germany",
		"nb_child": 4
	},
	{
		"name": "Cole Quinn",
		"age": 48,
		"country": "Belgium",
		"nb_child": 1
	}
]
